siganalysis/__init__.py
siganalysis/siganalysis.py
siganalysis-0.5.1.dist-info/METADATA
siganalysis-0.5.1.dist-info/WHEEL
siganalysis-0.5.1.dist-info/licenses/AUTHORS.md
siganalysis-0.5.1.dist-info/licenses/LICENSE.txt
siganalysis-0.5.1.dist-info/RECORD
