Metadata-Version: 2.4
Name: siganalysis
Version: 0.5.1
Summary: Perform signal analysis
Project-URL: Homepage, https://github.com/questrail/siganalysis
Project-URL: Issues, https://github.com/questrail/siganalysis/issues
Author-email: Matthew Rankin <matthew@questrail.com>
License-File: AUTHORS.md
License-File: LICENSE.txt
Classifier: Development Status :: 4 - Beta
Classifier: Intended Audience :: Developers
Classifier: License :: OSI Approved :: MIT License
Classifier: Operating System :: OS Independent
Classifier: Programming Language :: Python
Classifier: Programming Language :: Python :: 3
Classifier: Programming Language :: Python :: 3.12
Classifier: Programming Language :: Python :: 3.13
Classifier: Topic :: Software Development :: Libraries :: Python Modules
Requires-Python: >=3.12
Requires-Dist: matplotlib>=3.10.0
Requires-Dist: numpy>=2.2.0
Requires-Dist: scipy>=1.14.1
